telesto/__init__.py
telesto/app.py
telesto/config.py
telesto/logger.py
telesto/models.py
telesto/classification/__init__.py
telesto/classification/app.py
telesto/classification/model.py
telesto/instance_segmentation/__init__.py
telesto/instance_segmentation/app.py
telesto/instance_segmentation/model.py
tests/__init__.py
tests/segmentation/__init__.py
tests/segmentation/test_app.py
tests/segmentation/test_model.py
telesto_base-0.0.4.dist-info/LICENSE
telesto_base-0.0.4.dist-info/METADATA
telesto_base-0.0.4.dist-info/WHEEL
telesto_base-0.0.4.dist-info/top_level.txt
telesto_base-0.0.4.dist-info/RECORD
