Metadata-Version: 2.1
Name: telesto-base
Version: 0.0.4
Summary: Base tools for telesto.ai models
Home-page: https://github.com/telesto-ai/telesto-base
Author: telesto.ai
Author-email: contact@telesto.ai
License: UNKNOWN
Platform: UNKNOWN
Classifier: Programming Language :: Python :: 3
Classifier: License :: OSI Approved :: Apache Software License
Classifier: Operating System :: OS Independent
Requires-Python: >=3.6
Requires-Dist: numpy
Requires-Dist: Pillow
Requires-Dist: gunicorn (>=20.0)
Requires-Dist: falcon (>=2.0)
Requires-Dist: pytest
